<?xml version="1.0" encoding="iso-8859-1" ?>
<newsitem itemid="11308" id="root" date="1996-08-23" xml:lang="en">
<title>SINGAPORE: STC Singapore denies buying 250,000t palm oil.</title>
<headline>STC Singapore denies buying 250,000t palm oil.</headline>
<dateline>SINGAPORE 1996-08-23</dateline>
<text>
<p>The branch manager of India's State Trading Corporation (STC) office in Singapore said on Friday STC was not in the market for up to 250,000 tonnes of palm oil for September/October shipment as rumoured in the market.</p>
<p>Singapore dealers said talk was circulating that Indian buyers were purchasing around 250,000 tonnes of palm oil for shipment over this period.</p>
<p>&quot;We are not in the market for 250,000 tonnes of palm oil. We would never buy that quantity. We buy in lots of about 6,000 tonnes,&quot; the STC manager said.</p>
<p>Traders said that the talk was focusing on Indian buyers as a whole rather just STC.</p>
</text>
<copyright>(c) Reuters Limited 1996</copyright>
<metadata>
<codes class="bip:countries:1.0">
  <code code="INDIA">
    <editdetail attribution="Reuters BIP Coding Group" action="confirmed" date="1996-08-23"/>
  </code>
  <code code="SINGP">
    <editdetail attribution="Reuters BIP Coding Group" action="confirmed" date="1996-08-23"/>
  </code>
</codes>
<codes class="bip:topics:1.0">
  <code code="M14">
    <editdetail attribution="Reuters BIP Coding Group" action="confirmed" date="1996-08-23"/>
  </code>
  <code code="M141">
    <editdetail attribution="Reuters BIP Coding Group" action="confirmed" date="1996-08-23"/>
  </code>
  <code code="MCAT">
    <editdetail attribution="Reuters BIP Coding Group" action="confirmed" date="1996-08-23"/>
  </code>
</codes>
<dc element="dc.date.created" value="1996-08-23"/>
<dc element="dc.publisher" value="Reuters Holdings Plc"/>
<dc element="dc.date.published" value="1996-08-23"/>
<dc element="dc.source" value="Reuters"/>
<dc element="dc.creator.location" value="SINGAPORE"/>
<dc element="dc.creator.location.country.name" value="SINGAPORE"/>
<dc element="dc.source" value="Reuters"/>
</metadata>
</newsitem>
