<?xml version="1.0" encoding="iso-8859-1" ?>
<newsitem itemid="4911" id="root" date="1996-08-20" xml:lang="en">
<title>PORTUGAL: Yields could gain at Portugal 5-yr bond sale.</title>
<headline>Yields could gain at Portugal 5-yr bond sale.</headline>
<dateline>LISBON 1996-08-20</dateline>
<text>
<p>Yields could be slightly higher than secondary market levels at the Treasury's sale on Tuesday of up to 20 billion escudos of five-year bonds, analysts and traders said.</p>
<p>As a result, the Treasury may opt not to place all the paper, they added.</p>
<p>&quot;The yields bid will be certainly higher than eight percent and could reach 8.07 percent,&quot; said one trader.</p>
<p>He said the majority of the bids would probably be around 8.04 percent.</p>
<p>At the last sale of March 2001 bonds on July 25, the average yield was 8.0161 percent. The bonds closed at 8.0 percent on the secondary market on Monday.</p>
<p>Results of Tuesday's auction are due at around 1000 GMT.</p>
<p>Traders said the banks would be adopting a cautious line because of uncertainty over what the Federal Reserve might decide at its Open Market Committee meeting on Tuesday.</p>
<p>Any rate rise would be potentially damaging for peripheral bond markets such as Portugal, traders said.</p>
<p>They said that final investors were still out of the market and banks were seeking a premium to buy at the sale.</p>
<p>-- Lisbon bureau 3511-3150035</p>
</text>
<copyright>(c) Reuters Limited 1996</copyright>
<metadata>
<codes class="bip:countries:1.0">
  <code code="PORL">
    <editdetail attribution="Reuters BIP Coding Group" action="confirmed" date="1996-08-20"/>
  </code>
</codes>
<codes class="bip:topics:1.0">
  <code code="E21">
    <editdetail attribution="Reuters BIP Coding Group" action="confirmed" date="1996-08-20"/>
  </code>
  <code code="E212">
    <editdetail attribution="Reuters BIP Coding Group" action="confirmed" date="1996-08-20"/>
  </code>
  <code code="ECAT">
    <editdetail attribution="Reuters BIP Coding Group" action="confirmed" date="1996-08-20"/>
  </code>
  <code code="M12">
    <editdetail attribution="Reuters BIP Coding Group" action="confirmed" date="1996-08-20"/>
  </code>
  <code code="MCAT">
    <editdetail attribution="Reuters BIP Coding Group" action="confirmed" date="1996-08-20"/>
  </code>
</codes>
<dc element="dc.date.created" value="1996-08-20"/>
<dc element="dc.publisher" value="Reuters Holdings Plc"/>
<dc element="dc.date.published" value="1996-08-20"/>
<dc element="dc.source" value="Reuters"/>
<dc element="dc.creator.location" value="LISBON"/>
<dc element="dc.creator.location.country.name" value="PORTUGAL"/>
<dc element="dc.source" value="Reuters"/>
</metadata>
</newsitem>
