<?xml version="1.0" encoding="iso-8859-1" ?>
<newsitem itemid="6616" id="root" date="1996-08-21" xml:lang="en">
<title>BANGLADESH: Dhaka bourse gets international affiliation.</title>
<headline>Dhaka bourse gets international affiliation.</headline>
<dateline>DHAKA 1996-08-21</dateline>
<text>
<p>The Paris-based International Federation of Stock Exchanges has affiliated the Dhaka Stock Exchange (DSE), a DSE statement said on Wednesday.</p>
<p>It said the affiliation was the outcome of the &quot;recent quality performance&quot; of the DSE. The DSE is expecting full membership of the federation in the next few years, the statement added.</p>
</text>
<copyright>(c) Reuters Limited 1996</copyright>
<metadata>
<codes class="bip:countries:1.0">
  <code code="BANDH">
    <editdetail attribution="Reuters BIP Coding Group" action="confirmed" date="1996-08-21"/>
  </code>
</codes>
<codes class="bip:topics:1.0">
  <code code="M11">
    <editdetail attribution="Reuters BIP Coding Group" action="confirmed" date="1996-08-21"/>
  </code>
  <code code="MCAT">
    <editdetail attribution="Reuters BIP Coding Group" action="confirmed" date="1996-08-21"/>
  </code>
</codes>
<dc element="dc.date.created" value="1996-08-21"/>
<dc element="dc.publisher" value="Reuters Holdings Plc"/>
<dc element="dc.date.published" value="1996-08-21"/>
<dc element="dc.source" value="Reuters"/>
<dc element="dc.creator.location" value="DHAKA"/>
<dc element="dc.creator.location.country.name" value="BANGLADESH"/>
<dc element="dc.source" value="Reuters"/>
</metadata>
</newsitem>
