<?xml version="1.0" encoding="iso-8859-1" ?>
<newsitem itemid="7468" id="root" date="1996-08-21" xml:lang="en">
<title>TUNISIA: PRESS DIGEST - Tunisia - Aug 21.</title>
<headline>PRESS DIGEST - Tunisia - Aug 21.</headline>
<dateline>TUNIS 1996-08-21</dateline>
<text>
<p>These are the leading stories in the Tunisian press on Wednesday. Reuters has not verified these stories and does not vouch for their accuracy.</p>
<p>LA PRESSE</p>
<p>-President Ben Ali discusses road infrastructure projects with Equipment and Housing Minister Ali Chaouch.</p>
<p>LE TEMPS</p>
<p>- Tomato production sets a record with 540,000 tonnes this year.</p>
</text>
<copyright>(c) Reuters Limited 1996</copyright>
<metadata>
<codes class="bip:countries:1.0">
  <code code="TUNIS">
    <editdetail attribution="Reuters BIP Coding Group" action="confirmed" date="1996-08-21"/>
  </code>
</codes>
<codes class="bip:topics:1.0">
  <code code="GCAT">
    <editdetail attribution="Reuters BIP Coding Group" action="confirmed" date="1996-08-21"/>
  </code>
</codes>
<dc element="dc.date.created" value="1996-08-21"/>
<dc element="dc.publisher" value="Reuters Holdings Plc"/>
<dc element="dc.date.published" value="1996-08-21"/>
<dc element="dc.source" value="Reuters"/>
<dc element="dc.creator.location" value="TUNIS"/>
<dc element="dc.creator.location.country.name" value="TUNISIA"/>
<dc element="dc.source" value="Reuters"/>
</metadata>
</newsitem>
