<?xml version="1.0" encoding="iso-8859-1" ?>
<newsitem itemid="7524" id="root" date="1996-08-21" xml:lang="en">
<title>SWITZERLAND: CS Holding wage costs rise on bonus pay.</title>
<headline>CS Holding wage costs rise on bonus pay.</headline>
<dateline>ZURICH 1996-08-21</dateline>
<text>
<p>CS Holding said 80 percent of the increase in staff expenses in the first half of 1996 was due to bonus-related payments linked to good earnings performance.</p>
<p>CS Holding's staff costs rose 498 million Swiss francs to 2.9 billion francs in the first half with around 400 million of the rise accounted for by higher performance-related compensation accruals, it said in a six-month statement.</p>
<p>CS Holding's operating expenses rose 17 percent to 3.93 billion francs in the first half, while gross profit before taxes rose 24 percent to 2.5 billion.</p>
<p>Trading income also rose 24 percent to 1.9 billion.</p>
<p>At CS Holding's investment banking unit CS First Boston trading results were very strong for both fixed-income and equity paper and net income was the highest in the company's history.</p>
<p>While CSFB's first half revenue rose 37 percent, it said it continued to focus on cost controls.</p>
<p>Expenses in the first half of 1996 rose 33 percent, but excluding incentive compensation accruals, operating expenses in the first half were two percent lower than in the first half of last year, CSFB said.</p>
<p>-- Zurich Editorial +41 1 631 7340</p>
</text>
<copyright>(c) Reuters Limited 1996</copyright>
<metadata>
<codes class="bip:countries:1.0">
  <code code="SWITZ">
    <editdetail attribution="Reuters BIP Coding Group" action="confirmed" date="1996-08-21"/>
  </code>
</codes>
<codes class="bip:industries:1.0">
  <code code="I81402">
    <editdetail attribution="Reuters BIP Coding Group" action="confirmed" date="1996-08-21"/>
  </code>
</codes>
<codes class="bip:topics:1.0">
  <code code="C15">
    <editdetail attribution="Reuters BIP Coding Group" action="confirmed" date="1996-08-21"/>
  </code>
  <code code="C151">
    <editdetail attribution="Reuters BIP Coding Group" action="confirmed" date="1996-08-21"/>
  </code>
  <code code="C42">
    <editdetail attribution="Reuters BIP Coding Group" action="confirmed" date="1996-08-21"/>
  </code>
  <code code="CCAT">
    <editdetail attribution="Reuters BIP Coding Group" action="confirmed" date="1996-08-21"/>
  </code>
  <code code="E41">
    <editdetail attribution="Reuters BIP Coding Group" action="confirmed" date="1996-08-21"/>
  </code>
  <code code="ECAT">
    <editdetail attribution="Reuters BIP Coding Group" action="confirmed" date="1996-08-21"/>
  </code>
  <code code="GCAT">
    <editdetail attribution="Reuters BIP Coding Group" action="confirmed" date="1996-08-21"/>
  </code>
  <code code="GJOB">
    <editdetail attribution="Reuters BIP Coding Group" action="confirmed" date="1996-08-21"/>
  </code>
</codes>
<dc element="dc.date.created" value="1996-08-21"/>
<dc element="dc.publisher" value="Reuters Holdings Plc"/>
<dc element="dc.date.published" value="1996-08-21"/>
<dc element="dc.source" value="Reuters"/>
<dc element="dc.creator.location" value="ZURICH"/>
<dc element="dc.creator.location.country.name" value="SWITZERLAND"/>
<dc element="dc.source" value="Reuters"/>
</metadata>
</newsitem>
